cfgov_setup/__init__.py
cfgov_setup/tests.py
cfgov_setup-1.3.dist-info/LICENSE
cfgov_setup-1.3.dist-info/METADATA
cfgov_setup-1.3.dist-info/WHEEL
cfgov_setup-1.3.dist-info/entry_points.txt
cfgov_setup-1.3.dist-info/top_level.txt
cfgov_setup-1.3.dist-info/RECORD
