Metadata-Version: 2.1
Name: cfgov-setup
Version: 1.3
Summary: UNKNOWN
Home-page: https://github.com/cfpb/cfgov-django-setup
Maintainer: CFPB
Maintainer-email: tech@cfpb.gov
License: UNKNOWN
Platform: UNKNOWN
Provides-Extra: testing
Requires-Dist: coverage (>=4.5.4) ; extra == 'testing'
Requires-Dist: mock (>=2.0.0) ; extra == 'testing'
